optopsy/__init__.py
optopsy/checks.py
optopsy/core.py
optopsy/datafeeds.py
optopsy/definitions.py
optopsy/rules.py
optopsy/strategies.py
optopsy-2.0.3.dist-info/licenses/LICENSE
optopsy-2.0.3.dist-info/METADATA
optopsy-2.0.3.dist-info/WHEEL
optopsy-2.0.3.dist-info/top_level.txt
optopsy-2.0.3.dist-info/RECORD
